pyfirmata/__init__.py
pyfirmata/boards.py
pyfirmata/mockup.py
pyfirmata/pyfirmata.py
pyfirmata/util.py
pyFirmata-1.0.2.dist-info/DESCRIPTION.rst
pyFirmata-1.0.2.dist-info/METADATA
pyFirmata-1.0.2.dist-info/metadata.json
pyFirmata-1.0.2.dist-info/RECORD
pyFirmata-1.0.2.dist-info/top_level.txt
pyFirmata-1.0.2.dist-info/WHEEL
