Metadata-Version: 2.0
Name: pyFirmata
Version: 1.0.2
Summary: A Python interface for the Firmata procotol
Home-page: https://github.com/tino/pyFirmata
Author: Tino de Bruijn
Author-email: tinodb@gmail.com
License: UNKNOWN
Platform: UNKNOWN
Classifier: Development Status :: 4 - Beta
Classifier: Environment :: Other Environment
Classifier: Intended Audience :: Developers
Classifier: License :: OSI Approved :: MIT License
Classifier: Operating System :: OS Independent
Classifier: Programming Language :: Python
Classifier: Programming Language :: Python :: 2
Classifier: Programming Language :: Python :: 2.7
Classifier: Programming Language :: Python :: 3
Classifier: Programming Language :: Python :: 3.3
Classifier: Programming Language :: Python :: 3.4
Classifier: Topic :: Utilities
Classifier: Topic :: Home Automation
Requires-Dist: pyserial
